genomoncology/cli/__init__.py
genomoncology/cli/commands.py
genomoncology/cli/const.py
genomoncology/cli/options.py
genomoncology/cli/state.py
genomoncology/kms/__init__.py
genomoncology/kms/annotations.py
genomoncology/kms/contents.py
genomoncology/kms/diseases.py
genomoncology/kms/factory.py
genomoncology/kms/genes.py
genomoncology/kms/hpo.py
genomoncology/kms/match.py
genomoncology/kms/match_consolidated_therapies.py
genomoncology/kms/mega_match.py
genomoncology/kms/therapies.py
genomoncology/kms/transcripts.py
genomoncology/kms/trials.py
genomoncology/kms/variant_interpretations.py
genomoncology/parse/__init__.py
genomoncology/parse/doctypes.py
genomoncology/parse/ensures.py
genomoncology/parse/fieldtypes.py
genomoncology/parse/fusions.py
genomoncology/pipeline/__init__.py
genomoncology/pipeline/comparators.py
genomoncology/pipeline/converters.py
genomoncology/pipeline/filters.py
genomoncology/pipeline/runner.py
genomoncology/pipeline/sinks/__init__.py
genomoncology/pipeline/sinks/alterations.py
genomoncology/pipeline/sinks/annotations.py
genomoncology/pipeline/sinks/base.py
genomoncology/pipeline/sinks/excel.py
genomoncology/pipeline/sinks/tsv.py
genomoncology/pipeline/sinks/vcf.py
genomoncology/pipeline/sinks/warehouse.py
genomoncology/pipeline/sources/__init__.py
genomoncology/pipeline/sources/aggregated.py
genomoncology/pipeline/sources/annotations_filter.py
genomoncology/pipeline/sources/base.py
genomoncology/pipeline/sources/bed.py
genomoncology/pipeline/sources/const.py
genomoncology/pipeline/sources/delimited.py
genomoncology/pipeline/sources/excel.py
genomoncology/pipeline/sources/maf.py
genomoncology/pipeline/sources/paths.py
genomoncology/pipeline/sources/smart_lazy_file.py
genomoncology/pipeline/sources/xml.py
genomoncology/pipeline/sources/one_off_sources/__init__.py
genomoncology/pipeline/sources/one_off_sources/clinvar_xml.py
genomoncology/pipeline/sources/one_off_sources/mitomap.py
genomoncology/pipeline/sources/one_off_sources/mtdb.py
gocli-0.12.0.dist-info/METADATA
gocli-0.12.0.dist-info/WHEEL
gocli-0.12.0.dist-info/entry_points.txt
gocli-0.12.0.dist-info/top_level.txt
gocli-0.12.0.dist-info/RECORD
