Metadata-Version: 2.4
Name: gocli
Version: 0.12.0
Summary: gocli
Author-email: Ian Maurer <ian@genomoncology.com>
Classifier: Development Status :: 4 - Beta
Classifier: Intended Audience :: Developers
Classifier: License :: Other/Proprietary License
Classifier: Natural Language :: English
Classifier: Programming Language :: Python
Classifier: Programming Language :: Python :: 3.13
Classifier: Topic :: Scientific/Engineering :: Bio-Informatics
Requires-Python: >=3.13
Requires-Dist: click==8.1.7
Requires-Dist: pydantic>=2.0.0
Requires-Dist: cytoolz
Requires-Dist: glom
Requires-Dist: pygments
Requires-Dist: openpyxl
Requires-Dist: gosdk>=0.11.0
Requires-Dist: govcf>=0.10.0
Requires-Dist: pysolr>=3.10.0
Provides-Extra: dev
Requires-Dist: pytest>=8.4.2; extra == "dev"
Requires-Dist: pytest-asyncio>=1.1.0; extra == "dev"
Requires-Dist: mock>=5.2.0; extra == "dev"
Requires-Dist: flake8>=7.3.0; extra == "dev"
Requires-Dist: build>=1.3.0; extra == "dev"
